ai_code_reviewer/__init__.py
ai_code_reviewer/cli.py
ai_code_reviewer/containers.py
ai_code_reviewer/review.py
ai_code_reviewer/run_review.py
ai_code_reviewer/utils.py
ai_code_reviewer/reviewers/__init__.py
ai_code_reviewer/reviewers/base.py
ai_code_reviewer/reviewers/programming_principle.py
tests/__init__.py
tests/test_base.py
tests/test_cli.py
ai_code_reviewer-0.0.23.dist-info/LICENSE
ai_code_reviewer-0.0.23.dist-info/METADATA
ai_code_reviewer-0.0.23.dist-info/WHEEL
ai_code_reviewer-0.0.23.dist-info/entry_points.txt
ai_code_reviewer-0.0.23.dist-info/top_level.txt
ai_code_reviewer-0.0.23.dist-info/RECORD
