Metadata-Version: 2.1
Name: ai_code_reviewer
Version: 0.0.23
Summary: Useful classes extending langchain library
Home-page: https://github.com/dimitree54/ai_code_reviewer
Author: Dmitrii Rashchenko
Author-email: dimitree54@gmail.com
License: MIT
Classifier: Programming Language :: Python :: 3
Classifier: Operating System :: OS Independent
License-File: LICENSE
Requires-Dist: langchain ~=0.1
Requires-Dist: pydantic >=2
Requires-Dist: yid-langchain-extensions ~=0.4.42
Requires-Dist: openai <2,>=1
Requires-Dist: langchainhub ~=0.1
Requires-Dist: PyYAML ~=6.0.1
Requires-Dist: gitpython ~=3.1.42
Requires-Dist: langchain-openai
Requires-Dist: colorlog
Requires-Dist: dependency-injector ~=4.41.0
